tap_sharepointsites/__init__.py
tap_sharepointsites/client.py
tap_sharepointsites/streams.py
tap_sharepointsites/tap.py
tap_sharepointsites/tests/__init__.py
tap_sharepointsites/tests/configuration/__init__.py
tap_sharepointsites/tests/configuration/test_catalog.py
tap_sharepointsites/tests/configuration/test_responses.py
tap_sharepointsites/tests/test_core.py
tap_sharepointsites-0.0.1.dist-info/entry_points.txt
tap_sharepointsites-0.0.1.dist-info/WHEEL
tap_sharepointsites-0.0.1.dist-info/METADATA
tap_sharepointsites-0.0.1.dist-info/RECORD
