Metadata-Version: 2.1
Name: tap-sharepointsites
Version: 0.0.1
Summary: `tap-sharepointsites` is a Singer tap for sharepointsites, built with the Meltano Singer SDK.
License: Apache 2.0
Keywords: ELT,sharepointsites
Author: Henning Holgersen
Requires-Python: >=3.7.1,<3.11
Classifier: License :: Other/Proprietary License
Classifier: Programming Language :: Python :: 3
Classifier: Programming Language :: Python :: 3.8
Classifier: Programming Language :: Python :: 3.9
Classifier: Programming Language :: Python :: 3.10
Requires-Dist: azure-identity (>=1.11,<2.0)
Requires-Dist: requests (>=2.25.1,<3.0.0)
Requires-Dist: singer-sdk (>=0.11.1,<0.12.0)
